staged_primitives/__init__.py
staged_primitives/estimator.py
staged_primitives/sampler.py
staged_primitives/base/__init__.py
staged_primitives/base/staged_estimator.py
staged_primitives/base/staged_sampler.py
staged_primitives/qiskit/__init__.py
staged_primitives/qiskit/primitives/__init__.py
staged_primitives/utils/__init__.py
staged_primitives/utils/binary.py
staged_primitives/utils/circuits.py
staged_primitives/utils/time.py
staged_primitives/utils/operators/__init__.py
staged_primitives/utils/operators/decomposition.py
staged_primitives/utils/operators/paulis.py
staged_primitives/utils/results/__init__.py
staged_primitives/utils/results/counts.py
staged_primitives/utils/results/reckoning.py
staged_primitives-0.4.0.dist-info/LICENSE.txt
staged_primitives-0.4.0.dist-info/WHEEL
staged_primitives-0.4.0.dist-info/METADATA
staged_primitives-0.4.0.dist-info/RECORD
