Metadata-Version: 2.1
Name: staged-primitives
Version: 0.4.0
Summary: Backend based primitives defining a staged computational pipeline.
Keywords: quantum computing,primitives,qiskit,IBM
Author-email: Pedro Rivero <pedro.rivero@ibm.com>
Maintainer-email: Pedro Rivero <pedro.rivero@ibm.com>
Requires-Python: >=3.8
Classifier: Development Status :: 1 - Planning
Classifier: Intended Audience :: Developers
Classifier: Intended Audience :: Education
Classifier: Intended Audience :: Science/Research
Classifier: License :: OSI Approved :: Apache Software License
Classifier: Natural Language :: English
Classifier: Operating System :: MacOS
Classifier: Operating System :: POSIX :: Linux
Classifier: Operating System :: Microsoft :: Windows
Classifier: Programming Language :: Python :: 3.8
Classifier: Programming Language :: Python :: 3.9
Classifier: Programming Language :: Python :: 3.10
Classifier: Programming Language :: Python :: 3.11
Classifier: Topic :: Scientific/Engineering :: Physics
Requires-Dist: qiskit-terra >= 0.22.2
Requires-Dist: tox >= 3.25.1 ; extra == "dev"
Requires-Dist: pre-commit >= 2.19.0 ; extra == "dev"
Requires-Dist: commitizen >= 2.28.0 ; extra == "dev"
Requires-Dist: jupyter-sphinx >= 0.3.2 ; extra == "docs"
Requires-Dist: nbsphinx >= 0.8.8 ; extra == "docs"
Requires-Dist: reno >= 3.5.0 ; extra == "docs"
Requires-Dist: sphinx-autodoc-typehints >= 1.17.0 ; extra == "docs"
Requires-Dist: autoflake >= 1.7.6 ; extra == "lint"
Requires-Dist: black[jupyter] ~= 22.6.0 ; extra == "lint"
Requires-Dist: flake8 >= 4.0.1 ; extra == "lint"
Requires-Dist: isort >= 5.10.1 ; extra == "lint"
Requires-Dist: mypy >= 0.961 ; extra == "lint"
Requires-Dist: mypy-extensions >= 0.4.3 ; extra == "lint"
Requires-Dist: pylint >= 2.14.4 ; extra == "lint"
Requires-Dist: jupyter >= 1.0.0 ; extra == "notebook"
Requires-Dist: notebook >= 6.4.12 ; extra == "notebook"
Requires-Dist: qiskit-terra[visualization] >= 0.22.2 ; extra == "notebook"
Requires-Dist: qiskit-aer >= 0.11.0 ; extra == "notebook"
Requires-Dist: nbqa >= 1.3.1 ; extra == "notebook"
Requires-Dist: treon >= 0.1.3 ; extra == "notebook"
Requires-Dist: pytest >= 7.1.2 ; extra == "test"
Requires-Dist: pytest-cov >= 3.0.0 ; extra == "test"
Requires-Dist: pytest-randomly >= 3.12.0 ; extra == "test"
Requires-Dist: qiskit-aer >= 0.11.0 ; extra == "test"
Project-URL: Documentation, https://github.com/Qiskit-Extensions/staged-primitives/tree/main/docs/
Project-URL: Download, https://pypi.org/project/staged-primitives/
Project-URL: Home, https://qiskit-community.github.io/prototypes/
Project-URL: Repository, https://github.com/Qiskit-Extensions/staged-primitives/
Provides-Extra: dev
Provides-Extra: docs
Provides-Extra: lint
Provides-Extra: notebook
Provides-Extra: test
